MANIFEST.in
README.md
TODO.md
requirements.txt
setup.py
markdown2html.egg-info/PKG-INFO
markdown2html.egg-info/SOURCES.txt
markdown2html.egg-info/dependency_links.txt
markdown2html.egg-info/entry_points.txt
markdown2html.egg-info/requires.txt
markdown2html.egg-info/top_level.txt
md2html/__init__.py
md2html/convert.py
md2html/style-templates/style.css